{"12928":[

	{
		"brgycode" : "12928001",
		"brgydesc" : "Binalayangan",
		"citymuncode" : "12928"
	},
	{
		"brgycode" : "12928002",
		"brgydesc" : "Binongan",
		"citymuncode" : "12928"
	},
	{
		"brgycode" : "12928003",
		"brgydesc" : "Borobor",
		"citymuncode" : "12928"
	},
	{
		"brgycode" : "12928004",
		"brgydesc" : "Cabaritan",
		"citymuncode" : "12928"
	},
	{
		"brgycode" : "12928005",
		"brgydesc" : "Cabigbigaan",
		"citymuncode" : "12928"
	},
	{
		"brgycode" : "12928006",
		"brgydesc" : "Calautit",
		"citymuncode" : "12928"
	},
	{
		"brgycode" : "12928007",
		"brgydesc" : "Calay-ab",
		"citymuncode" : "12928"
	},
	{
		"brgycode" : "12928008",
		"brgydesc" : "Camestizoan",
		"citymuncode" : "12928"
	},
	{
		"brgycode" : "12928009",
		"brgydesc" : "Casili",
		"citymuncode" : "12928"
	},
	{
		"brgycode" : "12928010",
		"brgydesc" : "Flora",
		"citymuncode" : "12928"
	},
	{
		"brgycode" : "12928011",
		"brgydesc" : "Lagatit",
		"citymuncode" : "12928"
	},
	{
		"brgycode" : "12928012",
		"brgydesc" : "Laoingen",
		"citymuncode" : "12928"
	},
	{
		"brgycode" : "12928013",
		"brgydesc" : "Lussoc",
		"citymuncode" : "12928"
	},
	{
		"brgycode" : "12928014",
		"brgydesc" : "Nalasin",
		"citymuncode" : "12928"
	},
	{
		"brgycode" : "12928015",
		"brgydesc" : "Nagbettedan",
		"citymuncode" : "12928"
	},
	{
		"brgycode" : "12928016",
		"brgydesc" : "Naglaoa-an",
		"citymuncode" : "12928"
	},
	{
		"brgycode" : "12928017",
		"brgydesc" : "Nambaran",
		"citymuncode" : "12928"
	},
	{
		"brgycode" : "12928018",
		"brgydesc" : "Nanerman",
		"citymuncode" : "12928"
	},
	{
		"brgycode" : "12928019",
		"brgydesc" : "Napo",
		"citymuncode" : "12928"
	},
	{
		"brgycode" : "12928020",
		"brgydesc" : "Padu Chico",
		"citymuncode" : "12928"
	},
	{
		"brgycode" : "12928021",
		"brgydesc" : "Padu Grande",
		"citymuncode" : "12928"
	},
	{
		"brgycode" : "12928022",
		"brgydesc" : "Paguraper",
		"citymuncode" : "12928"
	},
	{
		"brgycode" : "12928023",
		"brgydesc" : "Panay",
		"citymuncode" : "12928"
	},
	{
		"brgycode" : "12928024",
		"brgydesc" : "Pangpangdan",
		"citymuncode" : "12928"
	},
	{
		"brgycode" : "12928025",
		"brgydesc" : "Parada",
		"citymuncode" : "12928"
	},
	{
		"brgycode" : "12928026",
		"brgydesc" : "Paras",
		"citymuncode" : "12928"
	},
	{
		"brgycode" : "12928027",
		"brgydesc" : "Poblacion",
		"citymuncode" : "12928"
	},
	{
		"brgycode" : "12928030",
		"brgydesc" : "Puerta Real",
		"citymuncode" : "12928"
	},
	{
		"brgycode" : "12928031",
		"brgydesc" : "Pussuac",
		"citymuncode" : "12928"
	},
	{
		"brgycode" : "12928032",
		"brgydesc" : "Quimmarayan",
		"citymuncode" : "12928"
	},
	{
		"brgycode" : "12928033",
		"brgydesc" : "San Pablo",
		"citymuncode" : "12928"
	},
	{
		"brgycode" : "12928034",
		"brgydesc" : "Santa Cruz",
		"citymuncode" : "12928"
	},
	{
		"brgycode" : "12928035",
		"brgydesc" : "Santo Tomas",
		"citymuncode" : "12928"
	},
	{
		"brgycode" : "12928036",
		"brgydesc" : "Sived",
		"citymuncode" : "12928"
	},
	{
		"brgycode" : "12928038",
		"brgydesc" : "Vacunero",
		"citymuncode" : "12928"
	},
	{
		"brgycode" : "12928039",
		"brgydesc" : "Suksukit",
		"citymuncode" : "12928"
	}
]}