{"140120":[

	{
		"brgycode" : "140120001",
		"brgydesc" : "Bazar",
		"citymuncode" : "140120"
	},
	{
		"brgycode" : "140120002",
		"brgydesc" : "Bilabila",
		"citymuncode" : "140120"
	},
	{
		"brgycode" : "140120003",
		"brgydesc" : "Gangal (Pob.)",
		"citymuncode" : "140120"
	},
	{
		"brgycode" : "140120004",
		"brgydesc" : "Maguyepyep",
		"citymuncode" : "140120"
	},
	{
		"brgycode" : "140120005",
		"brgydesc" : "Naguilian",
		"citymuncode" : "140120"
	},
	{
		"brgycode" : "140120006",
		"brgydesc" : "Saccaang",
		"citymuncode" : "140120"
	},
	{
		"brgycode" : "140120007",
		"brgydesc" : "Sallapadan",
		"citymuncode" : "140120"
	},
	{
		"brgycode" : "140120008",
		"brgydesc" : "Subusob",
		"citymuncode" : "140120"
	},
	{
		"brgycode" : "140120009",
		"brgydesc" : "Ud-udiao",
		"citymuncode" : "140120"
	}
]}