{"141114":[
    {
		"brgycode" : "141114001",
		"brgydesc" : "Ambassador",
		"citymuncode" : "141114"
	},
	{
		"brgycode" : "141114002",
		"brgydesc" : "Ambongdolan",
		"citymuncode" : "141114"
	},
	{
		"brgycode" : "141114003",
		"brgydesc" : "Ba-ayan",
		"citymuncode" : "141114"
	},
	{
		"brgycode" : "141114004",
		"brgydesc" : "Basil",
		"citymuncode" : "141114"
	},
	{
		"brgycode" : "141114005",
		"brgydesc" : "Daclan",
		"citymuncode" : "141114"
	},
	{
		"brgycode" : "141114006",
		"brgydesc" : "Caponga (Pob.)",
		"citymuncode" : "141114"
	},
	{
		"brgycode" : "141114007",
		"brgydesc" : "Tublay Central",
		"citymuncode" : "141114"
	},
	{
		"brgycode" : "141114008",
		"brgydesc" : "Tuel",
		"citymuncode" : "141114"
	}
]}