{"142707":[

	{
		"brgycode" : "142707001",
		"brgydesc" : "Bangar",
		"citymuncode" : "142707"
	},
	{
		"brgycode" : "142707002",
		"brgydesc" : "Busilac",
		"citymuncode" : "142707"
	},
	{
		"brgycode" : "142707003",
		"brgydesc" : "Calimag",
		"citymuncode" : "142707"
	},
	{
		"brgycode" : "142707004",
		"brgydesc" : "Calupaan",
		"citymuncode" : "142707"
	},
	{
		"brgycode" : "142707005",
		"brgydesc" : "Caragasan",
		"citymuncode" : "142707"
	},
	{
		"brgycode" : "142707006",
		"brgydesc" : "Dolowog",
		"citymuncode" : "142707"
	},
	{
		"brgycode" : "142707007",
		"brgydesc" : "Kiling",
		"citymuncode" : "142707"
	},
	{
		"brgycode" : "142707008",
		"brgydesc" : "Namnama",
		"citymuncode" : "142707"
	},
	{
		"brgycode" : "142707009",
		"brgydesc" : "Namillangan",
		"citymuncode" : "142707"
	},
	{
		"brgycode" : "142707010",
		"brgydesc" : "Pinto",
		"citymuncode" : "142707"
	},
	{
		"brgycode" : "142707011",
		"brgydesc" : "Poblacion",
		"citymuncode" : "142707"
	},
	{
		"brgycode" : "142707013",
		"brgydesc" : "San Jose",
		"citymuncode" : "142707"
	},
	{
		"brgycode" : "142707014",
		"brgydesc" : "San Juan",
		"citymuncode" : "142707"
	},
	{
		"brgycode" : "142707015",
		"brgydesc" : "San Marcos",
		"citymuncode" : "142707"
	},
	{
		"brgycode" : "142707016",
		"brgydesc" : "San Quintin",
		"citymuncode" : "142707"
	},
	{
		"brgycode" : "142707017",
		"brgydesc" : "Santa Maria",
		"citymuncode" : "142707"
	},
	{
		"brgycode" : "142707018",
		"brgydesc" : "Santo Domingo (Cabicalan)",
		"citymuncode" : "142707"
	},
	{
		"brgycode" : "142707019",
		"brgydesc" : "Little Tadian",
		"citymuncode" : "142707"
	},
	{
		"brgycode" : "142707020",
		"brgydesc" : "Ngileb",
		"citymuncode" : "142707"
	},
	{
		"brgycode" : "142707021",
		"brgydesc" : "Laya",
		"citymuncode" : "142707"
	}
]}