{"143208":[

	{
		"brgycode" : "143208001",
		"brgydesc" : "Ableg",
		"citymuncode" : "143208"
	},
	{
		"brgycode" : "143208002",
		"brgydesc" : "Balatoc",
		"citymuncode" : "143208"
	},
	{
		"brgycode" : "143208003",
		"brgydesc" : "Balinciagao Norte",
		"citymuncode" : "143208"
	},
	{
		"brgycode" : "143208005",
		"brgydesc" : "Cagaluan",
		"citymuncode" : "143208"
	},
	{
		"brgycode" : "143208007",
		"brgydesc" : "Colayo",
		"citymuncode" : "143208"
	},
	{
		"brgycode" : "143208008",
		"brgydesc" : "Dalupa",
		"citymuncode" : "143208"
	},
	{
		"brgycode" : "143208009",
		"brgydesc" : "Dangtalan",
		"citymuncode" : "143208"
	},
	{
		"brgycode" : "143208010",
		"brgydesc" : "Galdang (Casaloan)",
		"citymuncode" : "143208"
	},
	{
		"brgycode" : "143208011",
		"brgydesc" : "Guina-ang (Pob.)",
		"citymuncode" : "143208"
	},
	{
		"brgycode" : "143208012",
		"brgydesc" : "Magsilay",
		"citymuncode" : "143208"
	},
	{
		"brgycode" : "143208013",
		"brgydesc" : "Malucsad",
		"citymuncode" : "143208"
	},
	{
		"brgycode" : "143208014",
		"brgydesc" : "Pugong",
		"citymuncode" : "143208"
	},
	{
		"brgycode" : "143208015",
		"brgydesc" : "Balenciagao Sur",
		"citymuncode" : "143208"
	},
	{
		"brgycode" : "143208016",
		"brgydesc" : "Bagtayan",
		"citymuncode" : "143208"
	}
]}