{"153805":[

	{
		"brgycode" : "153805001",
		"brgydesc" : "Alip (Pob.)",
		"citymuncode" : "153805"
	},
	{
		"brgycode" : "153805003",
		"brgydesc" : "Damawato",
		"citymuncode" : "153805"
	},
	{
		"brgycode" : "153805004",
		"brgydesc" : "Katil",
		"citymuncode" : "153805"
	},
	{
		"brgycode" : "153805006",
		"brgydesc" : "Malala",
		"citymuncode" : "153805"
	},
	{
		"brgycode" : "153805007",
		"brgydesc" : "Mangadeg",
		"citymuncode" : "153805"
	},
	{
		"brgycode" : "153805008",
		"brgydesc" : "Manindolo",
		"citymuncode" : "153805"
	},
	{
		"brgycode" : "153805010",
		"brgydesc" : "Puya",
		"citymuncode" : "153805"
	},
	{
		"brgycode" : "153805011",
		"brgydesc" : "Sepaka",
		"citymuncode" : "153805"
	},
	{
		"brgycode" : "153805013",
		"brgydesc" : "Lomoyon",
		"citymuncode" : "153805"
	},
	{
		"brgycode" : "153805014",
		"brgydesc" : "Kalumenga (Kalumanga)",
		"citymuncode" : "153805"
	},
	{
		"brgycode" : "153805015",
		"brgydesc" : "Palao sa Buto",
		"citymuncode" : "153805"
	},
	{
		"brgycode" : "153805016",
		"brgydesc" : "Damalusay",
		"citymuncode" : "153805"
	},
	{
		"brgycode" : "153805017",
		"brgydesc" : "Bonawan",
		"citymuncode" : "153805"
	},
	{
		"brgycode" : "153805018",
		"brgydesc" : "Bulod",
		"citymuncode" : "153805"
	},
	{
		"brgycode" : "153805019",
		"brgydesc" : "Datang",
		"citymuncode" : "153805"
	},
	{
		"brgycode" : "153805020",
		"brgydesc" : "Elbebe",
		"citymuncode" : "153805"
	},
	{
		"brgycode" : "153805021",
		"brgydesc" : "Lipao",
		"citymuncode" : "153805"
	},
	{
		"brgycode" : "153805022",
		"brgydesc" : "Madidis",
		"citymuncode" : "153805"
	},
	{
		"brgycode" : "153805023",
		"brgydesc" : "Makat",
		"citymuncode" : "153805"
	},
	{
		"brgycode" : "153805024",
		"brgydesc" : "Mao",
		"citymuncode" : "153805"
	},
	{
		"brgycode" : "153805025",
		"brgydesc" : "Napok",
		"citymuncode" : "153805"
	},
	{
		"brgycode" : "153805026",
		"brgydesc" : "Poblacion",
		"citymuncode" : "153805"
	},
	{
		"brgycode" : "153805027",
		"brgydesc" : "Salendab",
		"citymuncode" : "153805"
	}
]}