{"156609":[


	{
		"brgycode" : "156609001",
		"brgydesc" : "Kaha",
		"citymuncode" : "156609"
	},
	{
		"brgycode" : "156609002",
		"brgydesc" : "Alu Pangkoh",
		"citymuncode" : "156609"
	},
	{
		"brgycode" : "156609003",
		"brgydesc" : "Bagsak",
		"citymuncode" : "156609"
	},
	{
		"brgycode" : "156609004",
		"brgydesc" : "Bawisan",
		"citymuncode" : "156609"
	},
	{
		"brgycode" : "156609005",
		"brgydesc" : "Biid",
		"citymuncode" : "156609"
	},
	{
		"brgycode" : "156609006",
		"brgydesc" : "Bukid",
		"citymuncode" : "156609"
	},
	{
		"brgycode" : "156609008",
		"brgydesc" : "Buli Bawang",
		"citymuncode" : "156609"
	},
	{
		"brgycode" : "156609009",
		"brgydesc" : "Buton",
		"citymuncode" : "156609"
	},
	{
		"brgycode" : "156609010",
		"brgydesc" : "Buton Mahablo",
		"citymuncode" : "156609"
	},
	{
		"brgycode" : "156609011",
		"brgydesc" : "Danapa",
		"citymuncode" : "156609"
	},
	{
		"brgycode" : "156609012",
		"brgydesc" : "Duyan Kabao",
		"citymuncode" : "156609"
	},
	{
		"brgycode" : "156609013",
		"brgydesc" : "Gimba Lagasan",
		"citymuncode" : "156609"
	},
	{
		"brgycode" : "156609015",
		"brgydesc" : "Kahoy Sinah",
		"citymuncode" : "156609"
	},
	{
		"brgycode" : "156609016",
		"brgydesc" : "Kanaway",
		"citymuncode" : "156609"
	},
	{
		"brgycode" : "156609017",
		"brgydesc" : "Kutah Sairap",
		"citymuncode" : "156609"
	},
	{
		"brgycode" : "156609019",
		"brgydesc" : "Lagasan Higad",
		"citymuncode" : "156609"
	},
	{
		"brgycode" : "156609021",
		"brgydesc" : "Laum Buwahan",
		"citymuncode" : "156609"
	},
	{
		"brgycode" : "156609023",
		"brgydesc" : "Laum Suwah",
		"citymuncode" : "156609"
	},
	{
		"brgycode" : "156609024",
		"brgydesc" : "Alu Layag-Layag",
		"citymuncode" : "156609"
	},
	{
		"brgycode" : "156609025",
		"brgydesc" : "Liang",
		"citymuncode" : "156609"
	},
	{
		"brgycode" : "156609026",
		"brgydesc" : "Linuho",
		"citymuncode" : "156609"
	},
	{
		"brgycode" : "156609027",
		"brgydesc" : "Lipunos",
		"citymuncode" : "156609"
	},
	{
		"brgycode" : "156609028",
		"brgydesc" : "Lungan Gitong",
		"citymuncode" : "156609"
	},
	{
		"brgycode" : "156609029",
		"brgydesc" : "Lumbaan Mahaba",
		"citymuncode" : "156609"
	},
	{
		"brgycode" : "156609030",
		"brgydesc" : "Lupa Abu",
		"citymuncode" : "156609"
	},
	{
		"brgycode" : "156609031",
		"brgydesc" : "Nonokan",
		"citymuncode" : "156609"
	},
	{
		"brgycode" : "156609032",
		"brgydesc" : "Paugan",
		"citymuncode" : "156609"
	},
	{
		"brgycode" : "156609033",
		"brgydesc" : "Payuhan",
		"citymuncode" : "156609"
	},
	{
		"brgycode" : "156609034",
		"brgydesc" : "Piyahan",
		"citymuncode" : "156609"
	},
	{
		"brgycode" : "156609035",
		"brgydesc" : "Poblacion (Parang)",
		"citymuncode" : "156609"
	},
	{
		"brgycode" : "156609036",
		"brgydesc" : "Saldang",
		"citymuncode" : "156609"
	},
	{
		"brgycode" : "156609037",
		"brgydesc" : "Sampunay",
		"citymuncode" : "156609"
	},
	{
		"brgycode" : "156609038",
		"brgydesc" : "Silangkan",
		"citymuncode" : "156609"
	},
	{
		"brgycode" : "156609039",
		"brgydesc" : "Taingting",
		"citymuncode" : "156609"
	},
	{
		"brgycode" : "156609040",
		"brgydesc" : "Tikong",
		"citymuncode" : "156609"
	},
	{
		"brgycode" : "156609041",
		"brgydesc" : "Tukay",
		"citymuncode" : "156609"
	},
	{
		"brgycode" : "156609042",
		"brgydesc" : "Tumangas",
		"citymuncode" : "156609"
	},
	{
		"brgycode" : "156609043",
		"brgydesc" : "Wanni Piyanjihan",
		"citymuncode" : "156609"
	},
	{
		"brgycode" : "156609044",
		"brgydesc" : "Lanao Dakula",
		"citymuncode" : "156609"
	},
	{
		"brgycode" : "156609045",
		"brgydesc" : "Lower Sampunay",
		"citymuncode" : "156609"
	}
]}