{"21526":[

	{
		"brgycode" : "21526001",
		"brgydesc" : "Abariongan Ruar",
		"citymuncode" : "21526"
	},
	{
		"brgycode" : "21526002",
		"brgydesc" : "Abariongan Uneg",
		"citymuncode" : "21526"
	},
	{
		"brgycode" : "21526003",
		"brgydesc" : "Balagan",
		"citymuncode" : "21526"
	},
	{
		"brgycode" : "21526004",
		"brgydesc" : "Balanni",
		"citymuncode" : "21526"
	},
	{
		"brgycode" : "21526006",
		"brgydesc" : "Cabayo",
		"citymuncode" : "21526"
	},
	{
		"brgycode" : "21526007",
		"brgydesc" : "Calapangan",
		"citymuncode" : "21526"
	},
	{
		"brgycode" : "21526008",
		"brgydesc" : "Calassitan",
		"citymuncode" : "21526"
	},
	{
		"brgycode" : "21526009",
		"brgydesc" : "Campo",
		"citymuncode" : "21526"
	},
	{
		"brgycode" : "21526010",
		"brgydesc" : "Centro Norte (Pob.)",
		"citymuncode" : "21526"
	},
	{
		"brgycode" : "21526011",
		"brgydesc" : "Centro Sur (Pob.)",
		"citymuncode" : "21526"
	},
	{
		"brgycode" : "21526012",
		"brgydesc" : "Dungao",
		"citymuncode" : "21526"
	},
	{
		"brgycode" : "21526014",
		"brgydesc" : "Lattac",
		"citymuncode" : "21526"
	},
	{
		"brgycode" : "21526015",
		"brgydesc" : "Lipatan",
		"citymuncode" : "21526"
	},
	{
		"brgycode" : "21526016",
		"brgydesc" : "Lubo",
		"citymuncode" : "21526"
	},
	{
		"brgycode" : "21526017",
		"brgydesc" : "Mabitbitnong",
		"citymuncode" : "21526"
	},
	{
		"brgycode" : "21526018",
		"brgydesc" : "Mapitac",
		"citymuncode" : "21526"
	},
	{
		"brgycode" : "21526019",
		"brgydesc" : "Masical",
		"citymuncode" : "21526"
	},
	{
		"brgycode" : "21526020",
		"brgydesc" : "Matalao",
		"citymuncode" : "21526"
	},
	{
		"brgycode" : "21526021",
		"brgydesc" : "Nag-uma",
		"citymuncode" : "21526"
	},
	{
		"brgycode" : "21526022",
		"brgydesc" : "Namuccayan",
		"citymuncode" : "21526"
	},
	{
		"brgycode" : "21526023",
		"brgydesc" : "Niug Norte",
		"citymuncode" : "21526"
	},
	{
		"brgycode" : "21526024",
		"brgydesc" : "Niug Sur",
		"citymuncode" : "21526"
	},
	{
		"brgycode" : "21526025",
		"brgydesc" : "Palusao",
		"citymuncode" : "21526"
	},
	{
		"brgycode" : "21526026",
		"brgydesc" : "San Manuel",
		"citymuncode" : "21526"
	},
	{
		"brgycode" : "21526027",
		"brgydesc" : "San Roque",
		"citymuncode" : "21526"
	},
	{
		"brgycode" : "21526028",
		"brgydesc" : "Santa Felicitas",
		"citymuncode" : "21526"
	},
	{
		"brgycode" : "21526029",
		"brgydesc" : "Santa Maria",
		"citymuncode" : "21526"
	},
	{
		"brgycode" : "21526030",
		"brgydesc" : "Sidiran",
		"citymuncode" : "21526"
	},
	{
		"brgycode" : "21526031",
		"brgydesc" : "Tabang",
		"citymuncode" : "21526"
	},
	{
		"brgycode" : "21526032",
		"brgydesc" : "Tamucco",
		"citymuncode" : "21526"
	},
	{
		"brgycode" : "21526033",
		"brgydesc" : "Virginia",
		"citymuncode" : "21526"
	}
]}