{"30805":[
    {
		"brgycode" : "30805001",
		"brgydesc" : "A. Rivera (Pob.)",
		"citymuncode" : "30805"
	},
	{
		"brgycode" : "30805002",
		"brgydesc" : "Almacen",
		"citymuncode" : "30805"
	},
	{
		"brgycode" : "30805003",
		"brgydesc" : "Bacong",
		"citymuncode" : "30805"
	},
	{
		"brgycode" : "30805004",
		"brgydesc" : "Balsic",
		"citymuncode" : "30805"
	},
	{
		"brgycode" : "30805005",
		"brgydesc" : "Bamban",
		"citymuncode" : "30805"
	},
	{
		"brgycode" : "30805006",
		"brgydesc" : "Burgos-Soliman (Pob.)",
		"citymuncode" : "30805"
	},
	{
		"brgycode" : "30805007",
		"brgydesc" : "Cataning (Pob.)",
		"citymuncode" : "30805"
	},
	{
		"brgycode" : "30805008",
		"brgydesc" : "Culis",
		"citymuncode" : "30805"
	},
	{
		"brgycode" : "30805009",
		"brgydesc" : "Daungan (Pob.)",
		"citymuncode" : "30805"
	},
	{
		"brgycode" : "30805010",
		"brgydesc" : "Mabiga",
		"citymuncode" : "30805"
	},
	{
		"brgycode" : "30805011",
		"brgydesc" : "Mabuco",
		"citymuncode" : "30805"
	},
	{
		"brgycode" : "30805012",
		"brgydesc" : "Maite",
		"citymuncode" : "30805"
	},
	{
		"brgycode" : "30805013",
		"brgydesc" : "Mambog - Mandama",
		"citymuncode" : "30805"
	},
	{
		"brgycode" : "30805014",
		"brgydesc" : "Palihan",
		"citymuncode" : "30805"
	},
	{
		"brgycode" : "30805015",
		"brgydesc" : "Pandatung",
		"citymuncode" : "30805"
	},
	{
		"brgycode" : "30805016",
		"brgydesc" : "Pulo",
		"citymuncode" : "30805"
	},
	{
		"brgycode" : "30805017",
		"brgydesc" : "Saba",
		"citymuncode" : "30805"
	},
	{
		"brgycode" : "30805019",
		"brgydesc" : "San Pedro (Pob.)",
		"citymuncode" : "30805"
	},
	{
		"brgycode" : "30805020",
		"brgydesc" : "Santo Cristo (Pob.)",
		"citymuncode" : "30805"
	},
	{
		"brgycode" : "30805021",
		"brgydesc" : "Sumalo",
		"citymuncode" : "30805"
	},
	{
		"brgycode" : "30805023",
		"brgydesc" : "Tipo",
		"citymuncode" : "30805"
	},
	{
		"brgycode" : "30805024",
		"brgydesc" : "Judge Roman Cruz Sr. (Mandama)",
		"citymuncode" : "30805"
	},
	{
		"brgycode" : "30805025",
		"brgydesc" : "Sacrifice Valley",
		"citymuncode" : "30805"
	}
]}