{"34919":[

	{
		"brgycode" : "34919001",
		"brgydesc" : "Aulo",
		"citymuncode" : "34919"
	},
	{
		"brgycode" : "34919003",
		"brgydesc" : "Bo. Militar (Fort Magsaysay)",
		"citymuncode" : "34919"
	},
	{
		"brgycode" : "34919004",
		"brgydesc" : "Ganaderia",
		"citymuncode" : "34919"
	},
	{
		"brgycode" : "34919005",
		"brgydesc" : "Maligaya",
		"citymuncode" : "34919"
	},
	{
		"brgycode" : "34919006",
		"brgydesc" : "Manacnac",
		"citymuncode" : "34919"
	},
	{
		"brgycode" : "34919007",
		"brgydesc" : "Mapait",
		"citymuncode" : "34919"
	},
	{
		"brgycode" : "34919008",
		"brgydesc" : "Marcos Village",
		"citymuncode" : "34919"
	},
	{
		"brgycode" : "34919010",
		"brgydesc" : "Malate (Pob.)",
		"citymuncode" : "34919"
	},
	{
		"brgycode" : "34919011",
		"brgydesc" : "Sapang Buho",
		"citymuncode" : "34919"
	},
	{
		"brgycode" : "34919012",
		"brgydesc" : "Singalat",
		"citymuncode" : "34919"
	},
	{
		"brgycode" : "34919013",
		"brgydesc" : "Atate",
		"citymuncode" : "34919"
	},
	{
		"brgycode" : "34919014",
		"brgydesc" : "Caballero",
		"citymuncode" : "34919"
	},
	{
		"brgycode" : "34919015",
		"brgydesc" : "Caimito",
		"citymuncode" : "34919"
	},
	{
		"brgycode" : "34919016",
		"brgydesc" : "Doña Josefa",
		"citymuncode" : "34919"
	},
	{
		"brgycode" : "34919017",
		"brgydesc" : "Imelda Valley",
		"citymuncode" : "34919"
	},
	{
		"brgycode" : "34919018",
		"brgydesc" : "Langka",
		"citymuncode" : "34919"
	},
	{
		"brgycode" : "34919020",
		"brgydesc" : "Santolan",
		"citymuncode" : "34919"
	},
	{
		"brgycode" : "34919021",
		"brgydesc" : "Popolon Pagas",
		"citymuncode" : "34919"
	},
	{
		"brgycode" : "34919022",
		"brgydesc" : "Bagong Buhay",
		"citymuncode" : "34919"
	}
]}