{"37108":[
    {
		"brgycode" : "37108001",
		"brgydesc" : "Alwa",
		"citymuncode" : "37108"
	},
	{
		"brgycode" : "37108002",
		"brgydesc" : "Bato",
		"citymuncode" : "37108"
	},
	{
		"brgycode" : "37108003",
		"brgydesc" : "Bulawen",
		"citymuncode" : "37108"
	},
	{
		"brgycode" : "37108004",
		"brgydesc" : "Cauyan",
		"citymuncode" : "37108"
	},
	{
		"brgycode" : "37108005",
		"brgydesc" : "Garreta",
		"citymuncode" : "37108"
	},
	{
		"brgycode" : "37108006",
		"brgydesc" : "Libaba",
		"citymuncode" : "37108"
	},
	{
		"brgycode" : "37108007",
		"brgydesc" : "Liozon",
		"citymuncode" : "37108"
	},
	{
		"brgycode" : "37108008",
		"brgydesc" : "Lipay",
		"citymuncode" : "37108"
	},
	{
		"brgycode" : "37108009",
		"brgydesc" : "Locloc",
		"citymuncode" : "37108"
	},
	{
		"brgycode" : "37108010",
		"brgydesc" : "Macarang",
		"citymuncode" : "37108"
	},
	{
		"brgycode" : "37108011",
		"brgydesc" : "Magalawa",
		"citymuncode" : "37108"
	},
	{
		"brgycode" : "37108012",
		"brgydesc" : "Pangolingan",
		"citymuncode" : "37108"
	},
	{
		"brgycode" : "37108013",
		"brgydesc" : "East Poblacion",
		"citymuncode" : "37108"
	},
	{
		"brgycode" : "37108015",
		"brgydesc" : "West Poblacion",
		"citymuncode" : "37108"
	},
	{
		"brgycode" : "37108016",
		"brgydesc" : "Salaza",
		"citymuncode" : "37108"
	},
	{
		"brgycode" : "37108017",
		"brgydesc" : "San Juan",
		"citymuncode" : "37108"
	},
	{
		"brgycode" : "37108018",
		"brgydesc" : "Santo Niño",
		"citymuncode" : "37108"
	},
	{
		"brgycode" : "37108019",
		"brgydesc" : "Santo Tomas",
		"citymuncode" : "37108"
	},
	{
		"brgycode" : "37108020",
		"brgydesc" : "Tition (San Vicente)",
		"citymuncode" : "37108"
	}
]}