{"37106":[
    {
		"brgycode" : "37106001",
		"brgydesc" : "Baloganon",
		"citymuncode" : "37106"
	},
	{
		"brgycode" : "37106002",
		"brgydesc" : "Bamban",
		"citymuncode" : "37106"
	},
	{
		"brgycode" : "37106003",
		"brgydesc" : "Bani",
		"citymuncode" : "37106"
	},
	{
		"brgycode" : "37106004",
		"brgydesc" : "Collat",
		"citymuncode" : "37106"
	},
	{
		"brgycode" : "37106005",
		"brgydesc" : "Inhobol",
		"citymuncode" : "37106"
	},
	{
		"brgycode" : "37106006",
		"brgydesc" : "North Poblacion",
		"citymuncode" : "37106"
	},
	{
		"brgycode" : "37106007",
		"brgydesc" : "San Lorenzo",
		"citymuncode" : "37106"
	},
	{
		"brgycode" : "37106008",
		"brgydesc" : "San Salvador",
		"citymuncode" : "37106"
	},
	{
		"brgycode" : "37106009",
		"brgydesc" : "Santa Rita",
		"citymuncode" : "37106"
	},
	{
		"brgycode" : "37106010",
		"brgydesc" : "Santo Rosario",
		"citymuncode" : "37106"
	},
	{
		"brgycode" : "37106011",
		"brgydesc" : "South Poblacion",
		"citymuncode" : "37106"
	},
	{
		"brgycode" : "37106012",
		"brgydesc" : "Taltal",
		"citymuncode" : "37106"
	},
	{
		"brgycode" : "37106013",
		"brgydesc" : "Tapuac",
		"citymuncode" : "37106"
	}
]}