{"45649":[

	{
		"brgycode" : "45649001",
		"brgydesc" : "Almacen",
		"citymuncode" : "45649"
	},
	{
		"brgycode" : "45649002",
		"brgydesc" : "Balagtas",
		"citymuncode" : "45649"
	},
	{
		"brgycode" : "45649003",
		"brgydesc" : "Balanacan",
		"citymuncode" : "45649"
	},
	{
		"brgycode" : "45649005",
		"brgydesc" : "Bulo Ibaba",
		"citymuncode" : "45649"
	},
	{
		"brgycode" : "45649006",
		"brgydesc" : "Bulo Ilaya",
		"citymuncode" : "45649"
	},
	{
		"brgycode" : "45649007",
		"brgydesc" : "Bonifacio",
		"citymuncode" : "45649"
	},
	{
		"brgycode" : "45649008",
		"brgydesc" : "Burgos",
		"citymuncode" : "45649"
	},
	{
		"brgycode" : "45649009",
		"brgydesc" : "Caigdal",
		"citymuncode" : "45649"
	},
	{
		"brgycode" : "45649010",
		"brgydesc" : "General Luna",
		"citymuncode" : "45649"
	},
	{
		"brgycode" : "45649011",
		"brgydesc" : "Kalilayan Ibaba",
		"citymuncode" : "45649"
	},
	{
		"brgycode" : "45649012",
		"brgydesc" : "Cabulihan Ibaba",
		"citymuncode" : "45649"
	},
	{
		"brgycode" : "45649013",
		"brgydesc" : "Mairok Ibaba",
		"citymuncode" : "45649"
	},
	{
		"brgycode" : "45649014",
		"brgydesc" : "Kalilayan Ilaya",
		"citymuncode" : "45649"
	},
	{
		"brgycode" : "45649015",
		"brgydesc" : "Cabulihan Ilaya",
		"citymuncode" : "45649"
	},
	{
		"brgycode" : "45649016",
		"brgydesc" : "Mabini",
		"citymuncode" : "45649"
	},
	{
		"brgycode" : "45649017",
		"brgydesc" : "Mairok Ilaya",
		"citymuncode" : "45649"
	},
	{
		"brgycode" : "45649018",
		"brgydesc" : "Malvar",
		"citymuncode" : "45649"
	},
	{
		"brgycode" : "45649019",
		"brgydesc" : "Maputat",
		"citymuncode" : "45649"
	},
	{
		"brgycode" : "45649020",
		"brgydesc" : "Muliguin",
		"citymuncode" : "45649"
	},
	{
		"brgycode" : "45649021",
		"brgydesc" : "Pagaguasan",
		"citymuncode" : "45649"
	},
	{
		"brgycode" : "45649022",
		"brgydesc" : "Panaon Ibaba",
		"citymuncode" : "45649"
	},
	{
		"brgycode" : "45649023",
		"brgydesc" : "Panaon Ilaya",
		"citymuncode" : "45649"
	},
	{
		"brgycode" : "45649024",
		"brgydesc" : "Plaridel",
		"citymuncode" : "45649"
	},
	{
		"brgycode" : "45649025",
		"brgydesc" : "F. De Jesus (Pob.)",
		"citymuncode" : "45649"
	},
	{
		"brgycode" : "45649026",
		"brgydesc" : "R. Lapu-lapu (Pob.)",
		"citymuncode" : "45649"
	},
	{
		"brgycode" : "45649027",
		"brgydesc" : "Raja Soliman (Pob.)",
		"citymuncode" : "45649"
	},
	{
		"brgycode" : "45649028",
		"brgydesc" : "R. Magsaysay (Pob.)",
		"citymuncode" : "45649"
	},
	{
		"brgycode" : "45649029",
		"brgydesc" : "Poctol",
		"citymuncode" : "45649"
	},
	{
		"brgycode" : "45649030",
		"brgydesc" : "Punta",
		"citymuncode" : "45649"
	},
	{
		"brgycode" : "45649031",
		"brgydesc" : "Rizal Ibaba",
		"citymuncode" : "45649"
	},
	{
		"brgycode" : "45649032",
		"brgydesc" : "Rizal Ilaya",
		"citymuncode" : "45649"
	},
	{
		"brgycode" : "45649033",
		"brgydesc" : "San Roque",
		"citymuncode" : "45649"
	},
	{
		"brgycode" : "45649034",
		"brgydesc" : "Socorro",
		"citymuncode" : "45649"
	},
	{
		"brgycode" : "45649035",
		"brgydesc" : "Tagumpay",
		"citymuncode" : "45649"
	},
	{
		"brgycode" : "45649036",
		"brgydesc" : "Tubas",
		"citymuncode" : "45649"
	},
	{
		"brgycode" : "45649037",
		"brgydesc" : "Tubigan",
		"citymuncode" : "45649"
	}
]}