{"54117":[

	{
		"brgycode" : "54117001",
		"brgydesc" : "Aguada",
		"citymuncode" : "54117"
	},
	{
		"brgycode" : "54117002",
		"brgydesc" : "Ban-Ao",
		"citymuncode" : "54117"
	},
	{
		"brgycode" : "54117003",
		"brgydesc" : "Burabod",
		"citymuncode" : "54117"
	},
	{
		"brgycode" : "54117004",
		"brgydesc" : "Cabangcalan",
		"citymuncode" : "54117"
	},
	{
		"brgycode" : "54117005",
		"brgydesc" : "Calumpang",
		"citymuncode" : "54117"
	},
	{
		"brgycode" : "54117006",
		"brgydesc" : "Camayabsan",
		"citymuncode" : "54117"
	},
	{
		"brgycode" : "54117008",
		"brgydesc" : "Daanlungsod",
		"citymuncode" : "54117"
	},
	{
		"brgycode" : "54117009",
		"brgydesc" : "Dangpanan",
		"citymuncode" : "54117"
	},
	{
		"brgycode" : "54117010",
		"brgydesc" : "Daraga",
		"citymuncode" : "54117"
	},
	{
		"brgycode" : "54117011",
		"brgydesc" : "Guin-Awayan",
		"citymuncode" : "54117"
	},
	{
		"brgycode" : "54117012",
		"brgydesc" : "Guinhan-Ayan",
		"citymuncode" : "54117"
	},
	{
		"brgycode" : "54117013",
		"brgydesc" : "Katipunan",
		"citymuncode" : "54117"
	},
	{
		"brgycode" : "54117014",
		"brgydesc" : "Libas",
		"citymuncode" : "54117"
	},
	{
		"brgycode" : "54117015",
		"brgydesc" : "Locso-An",
		"citymuncode" : "54117"
	},
	{
		"brgycode" : "54117016",
		"brgydesc" : "Luna",
		"citymuncode" : "54117"
	},
	{
		"brgycode" : "54117017",
		"brgydesc" : "Mahayag",
		"citymuncode" : "54117"
	},
	{
		"brgycode" : "54117018",
		"brgydesc" : "Mahayahay",
		"citymuncode" : "54117"
	},
	{
		"brgycode" : "54117019",
		"brgydesc" : "Manlut-Od",
		"citymuncode" : "54117"
	},
	{
		"brgycode" : "54117020",
		"brgydesc" : "Matagantang",
		"citymuncode" : "54117"
	},
	{
		"brgycode" : "54117021",
		"brgydesc" : "Naboctot",
		"citymuncode" : "54117"
	},
	{
		"brgycode" : "54117022",
		"brgydesc" : "Nagarao",
		"citymuncode" : "54117"
	},
	{
		"brgycode" : "54117023",
		"brgydesc" : "Nainday",
		"citymuncode" : "54117"
	},
	{
		"brgycode" : "54117024",
		"brgydesc" : "Naocondiot",
		"citymuncode" : "54117"
	},
	{
		"brgycode" : "54117025",
		"brgydesc" : "Pasiagon",
		"citymuncode" : "54117"
	},
	{
		"brgycode" : "54117026",
		"brgydesc" : "Pili",
		"citymuncode" : "54117"
	},
	{
		"brgycode" : "54117027",
		"brgydesc" : "Poblacion",
		"citymuncode" : "54117"
	},
	{
		"brgycode" : "54117028",
		"brgydesc" : "Puro",
		"citymuncode" : "54117"
	},
	{
		"brgycode" : "54117029",
		"brgydesc" : "Quibrada",
		"citymuncode" : "54117"
	},
	{
		"brgycode" : "54117030",
		"brgydesc" : "San Marcos",
		"citymuncode" : "54117"
	},
	{
		"brgycode" : "54117031",
		"brgydesc" : "Santa Cruz",
		"citymuncode" : "54117"
	},
	{
		"brgycode" : "54117032",
		"brgydesc" : "Taboc",
		"citymuncode" : "54117"
	},
	{
		"brgycode" : "54117033",
		"brgydesc" : "Tan-Awan",
		"citymuncode" : "54117"
	},
	{
		"brgycode" : "54117034",
		"brgydesc" : "Taverna",
		"citymuncode" : "54117"
	},
	{
		"brgycode" : "54117035",
		"brgydesc" : "Tubod",
		"citymuncode" : "54117"
	},
	{
		"brgycode" : "54117036",
		"brgydesc" : "Villa Inocencio",
		"citymuncode" : "54117"
	}
]}