{"54110":[
    {
		"brgycode" : "54110001",
		"brgydesc" : "Alas",
		"citymuncode" : "54110"
	},
	{
		"brgycode" : "54110002",
		"brgydesc" : "Ayat",
		"citymuncode" : "54110"
	},
	{
		"brgycode" : "54110003",
		"brgydesc" : "Bat-Ongan",
		"citymuncode" : "54110"
	},
	{
		"brgycode" : "54110004",
		"brgydesc" : "Bugtong",
		"citymuncode" : "54110"
	},
	{
		"brgycode" : "54110005",
		"brgydesc" : "Buri",
		"citymuncode" : "54110"
	},
	{
		"brgycode" : "54110006",
		"brgydesc" : "Cabitan",
		"citymuncode" : "54110"
	},
	{
		"brgycode" : "54110007",
		"brgydesc" : "Cagmasoso",
		"citymuncode" : "54110"
	},
	{
		"brgycode" : "54110008",
		"brgydesc" : "Canomoy",
		"citymuncode" : "54110"
	},
	{
		"brgycode" : "54110009",
		"brgydesc" : "Centro",
		"citymuncode" : "54110"
	},
	{
		"brgycode" : "54110010",
		"brgydesc" : "Dayao",
		"citymuncode" : "54110"
	},
	{
		"brgycode" : "54110011",
		"brgydesc" : "Guincaiptan",
		"citymuncode" : "54110"
	},
	{
		"brgycode" : "54110012",
		"brgydesc" : "Lantangan",
		"citymuncode" : "54110"
	},
	{
		"brgycode" : "54110013",
		"brgydesc" : "Looc",
		"citymuncode" : "54110"
	},
	{
		"brgycode" : "54110014",
		"brgydesc" : "Mabatobato",
		"citymuncode" : "54110"
	},
	{
		"brgycode" : "54110015",
		"brgydesc" : "Maolingon",
		"citymuncode" : "54110"
	},
	{
		"brgycode" : "54110016",
		"brgydesc" : "Nailaban",
		"citymuncode" : "54110"
	},
	{
		"brgycode" : "54110017",
		"brgydesc" : "Nanipsan",
		"citymuncode" : "54110"
	},
	{
		"brgycode" : "54110018",
		"brgydesc" : "Pinamangcaan",
		"citymuncode" : "54110"
	},
	{
		"brgycode" : "54110019",
		"brgydesc" : "Poblacion",
		"citymuncode" : "54110"
	},
	{
		"brgycode" : "54110020",
		"brgydesc" : "Polo Dacu",
		"citymuncode" : "54110"
	},
	{
		"brgycode" : "54110021",
		"brgydesc" : "San Juan",
		"citymuncode" : "54110"
	},
	{
		"brgycode" : "54110022",
		"brgydesc" : "San Pablo",
		"citymuncode" : "54110"
	},
	{
		"brgycode" : "54110023",
		"brgydesc" : "Santa Fe",
		"citymuncode" : "54110"
	},
	{
		"brgycode" : "54110024",
		"brgydesc" : "Tagpu",
		"citymuncode" : "54110"
	},
	{
		"brgycode" : "54110025",
		"brgydesc" : "Tumalaytay",
		"citymuncode" : "54110"
	},
	{
		"brgycode" : "54110026",
		"brgydesc" : "Laguinbanwa",
		"citymuncode" : "54110"
	}
]}